privato/__init__.py
privato/app/__init__.py
privato/app/dependencies.py
privato/app/main.py
privato/app/api/__init__.py
privato/app/api/routes/__init__.py
privato/app/api/routes/analyzer.py
privato/app/api/routes/api.py
privato/app/api/routes/redactor.py
privato/app/schemas/__init__.py
privato/app/schemas/analyzer.py
privato/app/static/__init__.py
privato/app/static/eslint.config.js
privato/app/static/index.html
privato/app/static/package-lock.json
privato/app/static/package.json
privato/app/static/vite.config.js
privato/app/static/dist/index.html
privato/app/static/dist/assets/index-DPFcWcAH.js
privato/app/static/dist/assets/index-cWxKdYAl.css
privato/app/static/node_modules/flatted/python/flatted.py
privato/cli/__init__.py
privato/cli/main.py
privato/cli/commands/__init__.py
privato/cli/commands/analyzer.py
privato/cli/commands/api.py
privato/cli/commands/redactor.py
privato/core/__init__.py
privato/core/analyzer.py
privato/core/analyzer_engine.py
privato/core/config.py
privato/core/converter.py
privato/core/file_reader.py
privato/core/image_analyzer_engine.py
privato/core/ingestion.py
privato/core/logging.py
privato/core/redactor.py
privato/core/save_files.py
privato/core/utils.py
privato/ml/__init__.py
privato/ml/inference.py
privato/ml/pull_models.py
privato/ml/model/__init__.py
privato/ml/model/model.pt
privato/ml/model/yolov8s.onnx
tests/__init__.py
privato-0.1.4.dist-info/METADATA
privato-0.1.4.dist-info/WHEEL
privato-0.1.4.dist-info/entry_points.txt
privato-0.1.4.dist-info/top_level.txt
privato-0.1.4.dist-info/RECORD
